dpd_lib/Authentication20.py
dpd_lib/EndOfDayServiceV10.py
dpd_lib/LoginServiceV21.py
dpd_lib/ParcelLifecycleServiceV20.py
dpd_lib/ParcelShopFinderServiceV50.py
dpd_lib/ShipmentServiceV33.py
dpd_lib/__init__.py
carrier.dpd-2023.3.dist-info/METADATA
carrier.dpd-2023.3.dist-info/WHEEL
carrier.dpd-2023.3.dist-info/top_level.txt
carrier.dpd-2023.3.dist-info/RECORD
